Workbook
Name aporte: Simulador!$C$10
Name aporte_sugerido: Simulador!$C$11
Name lista_perfis: Apoio!$F$4:$F$6
Name lista_tipos: Apoio!$H$4:$H$9
Name perfil: Simulador!$C$14
Name prazo: Simulador!$C$12
Name salario: Simulador!$C$9
Name taxa_mensal: Simulador!$C$13

Sheet Simulador
B2: FII Simulador de investimentos em Fundos Imobiliários
B5: Simulador de patrimônio, dividendos e distribuição de aportes
B7: CONFIGURAÇÕES | E7: RESULTADO DA SIMULAÇÃO | I7: SIMULAÇÃO COM 10% DO SALÁRIO
B9: Salário Mensal | C9: 5000 | E9: Patrimônio acumulado | F9: =FV(taxa_mensal,prazo*12,-aporte,0,0) -> 26343.155 | I9: Aporte sugerido | J9: =salario*10% -> 500
B10: Investimento Mensal | C10: 1000 | E10: Dividendos mensais | F10: =F9*taxa_mensal -> 210.74524 | I10: Patrimônio | J10: =FV(taxa_mensal,prazo*12,-aporte_sugerido,0,0) -> 13171.578
B11: Investimento sugerido (10%) | C11: =salario*10% -> 500 | E11: Total aportado | F11: =aporte*12*prazo -> 24000 | I11: Dividendos/mês | J11: =J10*taxa_mensal -> 105.37262
B12: Prazo (anos) | C12: 2 | E12: Rendimento mensal | F12: =taxa_mensal -> 0.008
B13: Rendimento Mensal | C13: 0.008
B14: Perfil | C14: Conservador
B17: PROJEÇÃO DE PATRIMÔNIO
B19: Prazo (anos) | C19: Patrimônio | F19: Dividendos/mês
B20: 2 | C20: =FV(taxa_mensal,B20*12,-aporte,0,0) -> 26343.155 | F20: =C20*taxa_mensal -> 210.74524
B21: 5 | C21: =FV(taxa_mensal,B21*12,-aporte,0,0) -> 76623.867 | F21: =C21*taxa_mensal -> 612.99093
B22: 10 | C22: =FV(taxa_mensal,B22*12,-aporte,0,0) -> 200217.47 | F22: =C22*taxa_mensal -> 1601.7398
B23: 20 | C23: =FV(taxa_mensal,B23*12,-aporte,0,0) -> 721131.22 | F23: =C23*taxa_mensal -> 5769.0498
B24: 30 | C24: =FV(taxa_mensal,B24*12,-aporte,0,0) -> 2076413.2 | F24: =C24*taxa_mensal -> 16611.306
B27: DIVISÃO DO APORTE POR TIPO DE FII
B29: Tipo de FII | C29: Percentual | D29: Aporte | F29: Chave composta
B30: Tijolo | C30: =VLOOKUP(F30,Apoio!$A$4:$D$21,4,FALSE) -> 0.35 | D30: =aporte*C30 -> 350 | F30: =perfil&"|"&B30 -> Conservador|Tijolo
B31: Papel | C31: =VLOOKUP(F31,Apoio!$A$4:$D$21,4,FALSE) -> 0.3 | D31: =aporte*C31 -> 300 | F31: =perfil&"|"&B31 -> Conservador|Papel
B32: Híbrido | C32: =VLOOKUP(F32,Apoio!$A$4:$D$21,4,FALSE) -> 0.15 | D32: =aporte*C32 -> 150 | F32: =perfil&"|"&B32 -> Conservador|Híbrido
B33: FOF | C33: =VLOOKUP(F33,Apoio!$A$4:$D$21,4,FALSE) -> 0.1 | D33: =aporte*C33 -> 100 | F33: =perfil&"|"&B33 -> Conservador|FOF
B34: Desenvolvimento | C34: =VLOOKUP(F34,Apoio!$A$4:$D$21,4,FALSE) -> 0.05 | D34: =aporte*C34 -> 50 | F34: =perfil&"|"&B34 -> Conservador|Desenvolvimento
B35: Agro | C35: =VLOOKUP(F35,Apoio!$A$4:$D$21,4,FALSE) -> 0.05 | D35: =aporte*C35 -> 50 | F35: =perfil&"|"&B35 -> Conservador|Agro
B36: TOTAL | C36: =SUM(C30:C35) -> 1 | D36: =SUM(D30:D35) -> 1000
B38: AVISO: Esta ferramenta é uma simulação educacional. Os resultados dependem das premissas informadas e não representam garantia de rentabilidade ou recomendação de investimento.
B41: FII • Simulador educacional de investimentos

Sheet Apoio
A1: FII VISION - BASE DE APOIO
A3: Chave | B3: Perfil | C3: Tipo de FII | D3: Percentual | F3: Perfis | H3: Tipos de FII
A4: Conservador|Tijolo | B4: Conservador | C4: Tijolo | D4: 0.35 | F4: Conservador | H4: Tijolo
A5: Conservador|Papel | B5: Conservador | C5: Papel | D5: 0.3 | F5: Moderado | H5: Papel
A6: Conservador|Híbrido | B6: Conservador | C6: Híbrido | D6: 0.15 | F6: Arrojado | H6: Híbrido
A7: Conservador|FOF | B7: Conservador | C7: FOF | D7: 0.1 | H7: FOF
A8: Conservador|Desenvolvimento | B8: Conservador | C8: Desenvolvimento | D8: 0.05 | H8: Desenvolvimento
A9: Conservador|Agro | B9: Conservador | C9: Agro | D9: 0.05 | H9: Agro
A10: Moderado|Tijolo | B10: Moderado | C10: Tijolo | D10: 0.25
A11: Moderado|Papel | B11: Moderado | C11: Papel | D11: 0.2 | F11: OBSERVAÇÃO_x000D_ _x000D_ Os percentuais utilizados nesta ferramenta são exemplos didáticos e não representam recomendação de investimento.
A12: Moderado|Híbrido | B12: Moderado | C12: Híbrido | D12: 0.2
A13: Moderado|FOF | B13: Moderado | C13: FOF | D13: 0.15
A14: Moderado|Desenvolvimento | B14: Moderado | C14: Desenvolvimento | D14: 0.1
A15: Moderado|Agro | B15: Moderado | C15: Agro | D15: 0.1
A16: Arrojado|Tijolo | B16: Arrojado | C16: Tijolo | D16: 0.15
A17: Arrojado|Papel | B17: Arrojado | C17: Papel | D17: 0.15
A18: Arrojado|Híbrido | B18: Arrojado | C18: Híbrido | D18: 0.2
A19: Arrojado|FOF | B19: Arrojado | C19: FOF | D19: 0.15
A20: Arrojado|Desenvolvimento | B20: Arrojado | C20: Desenvolvimento | D20: 0.2
A21: Arrojado|Agro | B21: Arrojado | C21: Agro | D21: 0.15
